fedhf/__init__.py
fedhf/algor/__init__.py
fedhf/algor/base.py
fedhf/algor/async_/__init__.py
fedhf/algor/async_/fedasync/__init__.py
fedhf/algor/async_/fedasync/default_params.yaml
fedhf/algor/async_/fedasync/fedasync_aggregator.py
fedhf/algor/async_/fedasync/fedasync_trainer.py
fedhf/algor/sync/__init__.py
fedhf/algor/sync/fedavg/__init__.py
fedhf/algor/sync/fedavg/default_params.yaml
fedhf/algor/sync/fedavg/fedavg_aggregator.py
fedhf/algor/sync/fedprox/__init__.py
fedhf/algor/sync/fedprox/default_params.yaml
fedhf/algor/sync/fedprox/fedprox_aggregator.py
fedhf/algor/sync/fedprox/fedprox_trainer.py
fedhf/api/__init__.py
fedhf/api/cfg/__init__.py
fedhf/api/cfg/cfg.py
fedhf/api/cfg/opts.py
fedhf/api/dpm/__init__.py
fedhf/api/dpm/gaussian.py
fedhf/api/dpm/laplace.py
fedhf/api/dpm/sensitivity.py
fedhf/api/logger/__init__.py
fedhf/api/logger/base_logger.py
fedhf/api/logger/logger.py
fedhf/api/metric/__init__.py
fedhf/api/metric/metric.py
fedhf/api/path/__init__.py
fedhf/api/path/path.py
fedhf/api/serial/__init__.py
fedhf/api/serial/deserializer.py
fedhf/api/serial/serializer.py
fedhf/api/type/__init__.py
fedhf/api/type/const.py
fedhf/api/utils/__init__.py
fedhf/component/__init__.py
fedhf/component/aggregator/__init__.py
fedhf/component/aggregator/async_aggregator.py
fedhf/component/aggregator/base_aggregator.py
fedhf/component/aggregator/sync_aggregator.py
fedhf/component/attactor/__init__.py
fedhf/component/attactor/base_attactor.py
fedhf/component/attactor/dlg_attactor.py
fedhf/component/encryptor/__init__.py
fedhf/component/encryptor/base_encryptor.py
fedhf/component/encryptor/dp_encryptor.py
fedhf/component/evaluator/__init__.py
fedhf/component/evaluator/base_evaluator.py
fedhf/component/evaluator/default_evaluator.py
fedhf/component/sampler/__init__.py
fedhf/component/sampler/base_sampler.py
fedhf/component/sampler/noniid_sampler.py
fedhf/component/sampler/random_sampler.py
fedhf/component/selector/__init__.py
fedhf/component/selector/base_selector.py
fedhf-0.3.0.dist-info/LICENSE
fedhf-0.3.0.dist-info/METADATA
fedhf-0.3.0.dist-info/WHEEL
fedhf-0.3.0.dist-info/top_level.txt
fedhf-0.3.0.dist-info/RECORD
