Metadata-Version: 2.1
Name: fedhf
Version: 0.3.0
Summary: A Federated Learning Framework which is Heterogeneous and Flexible.
Home-page: https://github.com/beiyuouo/fedhf
Author: Bingjie Yan
Author-email: bj.yan.pa@qq.com
Maintainer: Bingjie Yan
Maintainer-email: bj.yan.pa@qq.com
License: Apache-2.0 License
Keywords: federated learning,deep learning,pytorch,asynchronous federated learning,wandb
Classifier: Topic :: Scientific/Engineering
Classifier: Topic :: Scientific/Engineering :: Artificial Intelligence
Classifier: Topic :: Software Development
Classifier: Topic :: Software Development :: Libraries
Classifier: Topic :: Software Development :: Libraries :: Python Modules
Classifier: License :: OSI Approved :: Apache Software License
Classifier: Programming Language :: Python :: 3
Requires-Python: >=3.6
License-File: LICENSE
Requires-Dist: torch (>=1.8.2)
Requires-Dist: torchvision (>=0.9.2)
Requires-Dist: numpy
Requires-Dist: tqdm
Requires-Dist: wandb
Requires-Dist: ezkfg
Requires-Dist: pyyaml
Requires-Dist: urllib3 (==1.25.3)
Provides-Extra: dev
Requires-Dist: nox ; extra == 'dev'
Requires-Dist: pytest ; extra == 'dev'
Requires-Dist: mkdocs ; extra == 'dev'
Provides-Extra: test
Requires-Dist: pytest ; extra == 'test'
Requires-Dist: mkdocs ; extra == 'test'
